[
  {
    "title": "The Hydrogen Stream: Orica move forward with 50 MW hydrogen hub in Australia",
    "link": "https://www.pv-magazine.com/2026/07/03/the-hydrogen-stream-orica-move-forward-with-50-mw-hydrogen-hub-in-australia/",
    "date": "2026-07-03T12:17:45.000Z",
    "source": "PV Magazine"
  },
  {
    "title": "&#8216;Pivot, learn and continue&#8217;",
    "link": "https://www.pv-magazine.com/2026/07/03/pivot-learn-and-continue/",
    "date": "2026-07-03T11:00:00.000Z",
    "source": "PV Magazine"
  },
  {
    "title": "VIDEO: Fluence&#8217;s Lars Stephan on what data centres and cybersecurity developments mean for BESS in Europe",
    "link": "https://www.energy-storage.news/video-fluences-lars-stephan-on-what-data-centres-and-cybersecurity-developments-mean-for-bess-in-europe/",
    "date": "2026-07-03T10:15:13.000Z",
    "source": "Energy Storage News"
  },
  {
    "title": "&#8216;It&#8217;s really about flexibility&#8217;: FERC issues &#8216;show cause&#8217; orders to US grid operators on large load integration",
    "link": "https://www.energy-storage.news/its-really-about-flexibility-ferc-issues-show-cause-orders-to-us-grid-operators-on-large-load-integration/",
    "date": "2026-07-03T10:04:29.000Z",
    "source": "Energy Storage News"
  },
  {
    "title": "Mild oxalic acid process enables efficient indium recovery from heterojunction solar cells",
    "link": "https://www.pv-magazine.com/2026/07/03/mild-oxalic-acid-process-enables-efficient-indium-recovery-from-heterojunction-solar-cells/",
    "date": "2026-07-03T09:48:47.000Z",
    "source": "PV Magazine"
  },
  {
    "title": "EDF, Total, ACWA, Tesla, Gotion and Envision among qualified bidders for Saudi&#8217;s 12GWh BESS tender",
    "link": "https://www.energy-storage.news/edf-total-acwa-tesla-gotion-and-envision-qualified-bidders-saudis-12gwh-bess-tender/",
    "date": "2026-07-03T09:10:51.000Z",
    "source": "Energy Storage News"
  },
  {
    "title": "HiTHIUM showcases its 6.9 MWh, eight-hour LDES solution at The smarter E Europe",
    "link": "https://www.pv-magazine.com/2026/07/03/hithium-showcases-its-6-9-mwh-eight-hour-ldes-solution-at-the-smarter-e-europe/",
    "date": "2026-07-03T09:00:00.000Z",
    "source": "PV Magazine"
  },
  {
    "title": "Defying the residential storage shakeout: MOVA LumeGret bets on AI differentiation in crowded European market",
    "link": "https://www.energy-storage.news/defying-the-residential-storage-shakeout-mova-lumegret-bets-on-ai-differentiation-in-crowded-european-market/",
    "date": "2026-07-03T08:46:57.000Z",
    "source": "Energy Storage News"
  },
  {
    "title": "China moves to curb overcapacity in PV industry with mandatory energy consumption standards",
    "link": "https://www.pv-magazine.com/2026/07/03/china-moves-to-curb-pv-overcapacity-with-mandatory-energy-consumption-standards/",
    "date": "2026-07-03T08:26:42.000Z",
    "source": "PV Magazine"
  },
  {
    "title": "Chinese scientists build 27.3%-efficient inverted perovskite solar cell based on dual-molecule interface",
    "link": "https://www.pv-magazine.com/2026/07/03/chinese-scientists-build-27-3-efficient-inverted-perovskite-solar-cell-based-on-dual-molecule-interface/",
    "date": "2026-07-03T08:17:23.000Z",
    "source": "PV Magazine"
  },
  {
    "title": "Australia&#8217;s grid-scale battery storage fleet generates AU$17.98 million in the NEM as revenue capture reaches 32%",
    "link": "https://www.energy-storage.news/australias-grid-scale-battery-storage-fleet-generates-au17-98-million-in-the-nem-as-revenue-capture-reaches-32/",
    "date": "2026-07-03T07:55:52.000Z",
    "source": "Energy Storage News"
  },
  {
    "title": "AGL to deliver 10.2MWh battery storage microgrid for South Australia&#8217;s largest almond orchard",
    "link": "https://www.energy-storage.news/agl-to-deliver-10-2mwh-battery-storage-microgrid-for-south-australias-largest-almond-orchard/",
    "date": "2026-07-03T07:52:40.000Z",
    "source": "Energy Storage News"
  },
  {
    "title": "„Wir brauchen eine neue Gründerzeit“",
    "link": "https://battery-news.de/2026/07/03/wir-brauchen-eine-neue-gruenderzeit/",
    "date": "2026-07-03T07:30:00.000Z",
    "source": "Battery-News.de"
  },
  {
    "title": "CATL nimmt Lithium-Mine in Jiangxi wieder in Betrieb",
    "link": "https://battery-news.de/2026/07/03/catl-nimmt-lithium-mine-in-jiangxi-wieder-in-betrieb/",
    "date": "2026-07-03T06:00:00.000Z",
    "source": "Battery-News.de"
  },
  {
    "title": "IBPC 2026 verlängert Call for Abstracts bis 10. Juli",
    "link": "https://battery-news.de/2026/07/02/ibpc-2026-verlaengert-call-for-abstracts-bis-10-juli/",
    "date": "2026-07-02T06:00:00.000Z",
    "source": "Battery-News.de"
  },
  {
    "title": "Ford-CATL-Batterieprojekt in Michigan startet Produktion",
    "link": "https://battery-news.de/2026/07/01/ford-catl-batterieprojekt-in-michigan-startet-produktion/",
    "date": "2026-07-01T06:00:00.000Z",
    "source": "Battery-News.de"
  },
  {
    "title": "Sicona erhält 45 Millionen Dollar für Anodenmaterial-Produktion in Wollongong",
    "link": "https://battery-news.de/2026/06/30/sicona-erhaelt-45-millionen-dollar-fuer-anodenmaterial-produktion-in-wollongong/",
    "date": "2026-06-30T06:00:00.000Z",
    "source": "Battery-News.de"
  },
  {
    "title": "OCSiAl liefert Nanoröhren für PowerCo-Zellplattform in Salzgitter",
    "link": "https://battery-news.de/2026/06/29/ocsial-liefert-nanoroehren-fuer-powerco-zellplattform-in-salzgitter/",
    "date": "2026-06-29T06:00:00.000Z",
    "source": "Battery-News.de"
  }
]